Metadata-Version: 2.1
Name: muvimaker
Version: 0.3
Summary: A small package to generate moving pictures from sound
Home-page: https://github.com/JannisNe/muvimaker
Author: Jannis Necker
Author-email: jannis.necker@gmail.com
License: MIT
Project-URL: Bug Tracker, https://github.com/JannisNe/muvimaker/issues
Keywords: music video picture generation
Platform: UNKNOWN
Classifier: License :: OSI Approved :: MIT License
Classifier: Operating System :: OS Independent
Classifier: Programming Language :: Python :: 3.9
Requires-Python: >=3.9
License-File: LICENSE
Requires-Dist: moviepy (==1.0.3)
Requires-Dist: librosa (==0.8.1)
Requires-Dist: numpy (==1.21.4)
Requires-Dist: matplotlib (==3.5.1)
Requires-Dist: jupyterlab (==3.2.5)
Requires-Dist: pillow (==8.4.0)
Requires-Dist: gizeh (==0.1.11)
Requires-Dist: ffmpeg (==1.4)
Requires-Dist: coveralls
Requires-Dist: setuptools (==59.7.0)
Requires-Dist: scikit-image (==0.19.1)
Requires-Dist: face-recognition (==1.3.0)
